osv_reproducer/__init__.py
osv_reproducer/main.py
osv_reproducer/common/__init__.py
osv_reproducer/common/constants.py
osv_reproducer/controllers/__init__.py
osv_reproducer/controllers/base.py
osv_reproducer/core/__init__.py
osv_reproducer/core/exc.py
osv_reproducer/core/version.py
osv_reproducer/core/common/__init__.py
osv_reproducer/core/common/enums.py
osv_reproducer/core/interfaces/__init__.py
osv_reproducer/core/interfaces/docker.py
osv_reproducer/core/interfaces/file_provision.py
osv_reproducer/core/interfaces/gcs.py
osv_reproducer/core/interfaces/github.py
osv_reproducer/core/interfaces/oss_fuzz.py
osv_reproducer/core/interfaces/osv.py
osv_reproducer/core/models/__init__.py
osv_reproducer/core/models/context.py
osv_reproducer/core/models/project.py
osv_reproducer/core/models/report.py
osv_reproducer/core/models/result.py
osv_reproducer/handlers/__init__.py
osv_reproducer/handlers/docker.py
osv_reproducer/handlers/file_provision.py
osv_reproducer/handlers/gcs.py
osv_reproducer/handlers/github.py
osv_reproducer/handlers/oss_fuzz.py
osv_reproducer/handlers/osv.py
osv_reproducer/services/__init__.py
osv_reproducer/services/builder.py
osv_reproducer/services/context.py
osv_reproducer/services/reproducer.py
osv_reproducer/services/runner.py
osv_reproducer/services/verifier.py
osv_reproducer/utils/__init__.py
osv_reproducer/utils/parse/__init__.py
osv_reproducer/utils/parse/arguments.py
osv_reproducer/utils/parse/common.py
osv_reproducer/utils/parse/dockerfile.py
osv_reproducer/utils/parse/log.py
osv_reproducer/utils/parse/report.py
osv_reproducer-0.0.9.dist-info/licenses/LICENSE
osv_reproducer-0.0.9.dist-info/METADATA
osv_reproducer-0.0.9.dist-info/WHEEL
osv_reproducer-0.0.9.dist-info/entry_points.txt
osv_reproducer-0.0.9.dist-info/top_level.txt
osv_reproducer-0.0.9.dist-info/RECORD
