Metadata-Version: 2.4
Name: osv-reproducer
Version: 0.0.9
Summary: A reproducer component that can compile OSS-Fuzz projects at specific versions and run test cases
Author-email: Eduard Pinconschi <eduard.pinconschi@tecnico.ulisboa.pt>
License: Apache-2.0
Project-URL: repository, https://github.com/epicosy/osv-reproducer
Project-URL: homepage, https://github.com/epicosy/osv-reproducer
Classifier: Programming Language :: Python :: 3
Classifier: License :: OSI Approved :: Apache Software License
Classifier: Operating System :: OS Independent
Requires-Python: >=3.10
License-File: LICENSE
Requires-Dist: pydantic>=2.11.7
Requires-Dist: osv-utils>=0.3.10
Requires-Dist: docker>=7.1.0
Requires-Dist: google-cloud-storage>=2.18.2
Requires-Dist: github_lib>=0.8.2
Requires-Dist: cement>=3.0.14
Requires-Dist: Jinja2>=3.1.6
Requires-Dist: PyYAML>=6.0.2
Requires-Dist: colorlog>=6.9.0
Requires-Dist: tqdm>=4.67.1
Requires-Dist: GitPython>=3.1.44
Requires-Dist: sarif-pydantic>=0.5.3
Provides-Extra: dev
Requires-Dist: pytest; extra == "dev"
Requires-Dist: pytest-cov; extra == "dev"
Requires-Dist: black; extra == "dev"
Requires-Dist: coverage; extra == "dev"
Requires-Dist: isort; extra == "dev"
Requires-Dist: mypy; extra == "dev"
Requires-Dist: flake8; extra == "dev"
Requires-Dist: twine; extra == "dev"
Requires-Dist: build; extra == "dev"
Dynamic: license-file
